[
  {
    "name": "This is my header",
    "id": "1",
    "isExpanded": true,
    "isExpandable": true,
    "children": [
      {
        "name": "Something",
        "id": "1-1"
      },
      {
        "name": "Something else",
        "id": "1-2"
      }
    ]
  },
  {
    "name": "Card McCardygan",
    "id": "2",
    "icon": true,
    "isLoading": true,
    "children": [
      {
        "name": "I'm loading data",
        "id": "2-1"
      },
      {
        "name": "Something else",
        "id": "2-2"
      },
      {
        "name": "Pfft",
        "id": "2-3"
      }
    ]
  },
  {
    "name": "Tile McTily",
    "id": "3",
    "icon": true,
    "children": [
      {
        "name": "Something",
        "id": "3-1"
      },
      {
        "name": "Something else",
        "id": "3-2"
      }
    ]
  },
  {
    "name": "Collapsed card",
    "id": "4",
    "isExpanded": false,
    "isExpandable": true,
    "children": [
      {
        "name": "Such",
        "id": "4-1"
      },
      {
        "name": "Content",
        "id": "4-2"
      },
      {
        "name": "Such",
        "id": "4-3"
      },
      {
        "name": "Wow",
        "id": "4-4"
      },
      {
        "name": "This is,,",
        "id": "4-5"
      },
      {
        "name": "Getting",
        "id": "4-6"
      },
      {
        "name": "Ridiculous",
        "id": "4-7"
      },
      {
        "name": "Right",
        "id": "4-8"
      },
      {
        "name": "Naw",
        "id": "4-9"
      }
    ]
  },
  {
    "name": "Div McDivvy",
    "id": "5",
    "icon": true,
    "children": [
      {
        "name": "Something",
        "id": "5-1"
      },
      {
        "name": "Something else",
        "id": "5-2"
      },
      {
        "name": "Something",
        "id": "5-3"
      },
      {
        "name": "Something completely different",
        "id": "5-4"
      }
    ]
  },
  {
    "name": "There's content under me",
    "id": "6",
    "icon": true,
    "children": [
      {
        "name": "Something",
        "id": "6-1"
      },
      {
        "name": "Something else",
        "id": "6-2"
      },
      {
        "name": "Something else",
        "id": "6-3"
      }
    ]
  },
  {
    "name": "Wicked!",
    "isLoading": true,
    "id": "7",
    "children": [
      {
        "name": "I'm loading data",
        "id": "7-1"
      },
      {
        "name": "Something else",
        "id": "7-2"
      }
    ]
  },
  {
    "name": "Amazeballs!",
    "id": "8",
    "icon": true,
    "children": [
      {
        "name": "Something",
        "id": "8-1"
      },
      {
        "name": "Something else",
        "id": "8-2"
      },
      {
        "name": "Something",
        "id": "8-3"
      },
      {
        "name": "Something else",
        "id": "8-4"
      },
      {
        "name": "Something",
        "id": "8-5"
      }
    ]
  }
]
